Workbook
Name equity: Sheet1!$D$19
Name MonthlyInvestment: Sheet1!$D$16
Name PortfolioYield: Sheet1!$D$11
Name ReturnRate: Sheet1!$D$18
Name suggestion: Sheet1!$D$12
Name Years: Sheet1!$D$17

Sheet Sheet1
B8: SETTINGS
D9: Value
B10: Salary | D10: 3000
B11: Portfolio Yield | D11: 0.005
B12: Suggested Investment | D12: =D10*30% -> 900
B14: MONTHLY INVESTMENT
D15: Value
B16: How much to invest? | D16: 900
B17: For how long? | D17: 5
B18: Monthly return rate | D18: 0.0108
B19: Accumulated equity | D19: =FV(ReturnRate,Years*12,MonthlyInvestment)*-1 -> 75423.617
B20: Monthly dividends | D20: =equity*PortfolioYield -> 377.11809
B22: MONTHLY INVESTMENT - PROJECTIONS
B23: Period | C23: Accumulated Amount | D23: Monthly dividend
A24: 2 | B24: How much in 2 years? | C24: =FV(ReturnRate,$A24*12,MonthlyInvestment)*-1 -> 24507.777 | D24: =C24*PortfolioYield -> 122.53889
A25: 5 | B25: How much in 5 years? | C25: =FV(ReturnRate,$A25*12,MonthlyInvestment)*-1 -> 75423.617 | D25: =C25*PortfolioYield -> 377.11809
A26: 10 | B26: How much in 10 years? | C26: =FV(ReturnRate,$A26*12,MonthlyInvestment)*-1 -> 219111.9 | D26: =C26*PortfolioYield -> 1095.5595
A27: 20 | B27: How much in 20 years? | C27: =FV(ReturnRate,$A27*12,MonthlyInvestment)*-1 -> 1014344.1 | D27: =C27*PortfolioYield -> 5071.7205
A28: 30 | B28: How much in 30 years? | C28: =FV(ReturnRate,$A28*12,MonthlyInvestment)*-1 -> 3900514.3 | D28: =C28*PortfolioYield -> 19502.572
B30: PROFILE | D30: Conservative
B31: Monthly investment amount | D31: =MonthlyInvestment -> 900
B33: TYPE OF REIT(FII) | C33: Suggested % | D33: Amount
B34: Paper | C34: =VLOOKUP($D$30&"-"&B34,Profile!$A$3:$D$20,4,FALSE) -> 0.3 | D34: =C34*$D$31 -> 270
B35: Brick | C35: =VLOOKUP($D$30&"-"&B35,Profile!$A$3:$D$20,4,FALSE) -> 0.5 | D35: =C35*$D$31 -> 450
B36: Hybrid | C36: =VLOOKUP($D$30&"-"&B36,Profile!$A$3:$D$20,4,FALSE) -> 0.1 | D36: =C36*$D$31 -> 90
B37: Funds of Funds | C37: =VLOOKUP($D$30&"-"&B37,Profile!$A$3:$D$20,4,FALSE) -> 0.1 | D37: =C37*$D$31 -> 90
B38: Development | C38: =VLOOKUP($D$30&"-"&B38,Profile!$A$3:$D$20,4,FALSE) -> 0 | D38: =C38*$D$31 -> 0
B39: Hospitality | C39: =VLOOKUP($D$30&"-"&B39,Profile!$A$3:$D$20,4,FALSE) -> 0 | D39: =C39*$D$31 -> 0
B40: Total | D40: =SUM(D34:D39) -> 900
B58: SCENARIO ANALYSIS
B59: SCENARIO | D59: Base Case
B60: Monthly Return Rate | C60: Accumulated in 5 years | D60: Monthly Dividend
B61: {=_xlfn.XLOOKUP(D59,Scenario_Analysis!A2:A5,Scenario_Analysis!B2:D5)} -> 0.01 | C61: 73502.703 | D61: 735.02703

Sheet Scenario_Analysis
A1: SCENARIO ANALYSIS
A2: Scenario | B2: Monthly Return Rate | C2: Accumulated in 5 Years | D2: Monthly Dividend
A3: Worst Case | B3: 0.008 | C3: =FV(B3,Years*12,-MonthlyInvestment,0) -> 68961.48 | D3: =C3*B3 -> 551.69184
A4: Base Case | B4: 0.01 | C4: =FV(B4,Years*12,-MonthlyInvestment,0) -> 73502.703 | D4: =C4*B4 -> 735.02703
A5: Best Case | B5: 0.012 | C5: =FV(B5,Years*12,-MonthlyInvestment,0) -> 78423.545 | D5: =C5*B5 -> 941.08254
A8: Month | B8: Accumulated Value
A9: 1 | B9: =FV( _xlfn.XLOOKUP(Sheet1!$D$59,Scenario_Analysis!$A$3:$A$5,Scenario_Analysis!$B$3:$B$5),Scenario_Analysis!A9,-MonthlyInvestment,0) -> 900
A10: 2 | B10: =FV( _xlfn.XLOOKUP(Sheet1!$D$59,Scenario_Analysis!$A$3:$A$5,Scenario_Analysis!$B$3:$B$5),Scenario_Analysis!A10,-MonthlyInvestment,0) -> 1809
A11: 3 | B11: =FV( _xlfn.XLOOKUP(Sheet1!$D$59,Scenario_Analysis!$A$3:$A$5,Scenario_Analysis!$B$3:$B$5),Scenario_Analysis!A11,-MonthlyInvestment,0) -> 2727.09
A12: 4 | B12: =FV( _xlfn.XLOOKUP(Sheet1!$D$59,Scenario_Analysis!$A$3:$A$5,Scenario_Analysis!$B$3:$B$5),Scenario_Analysis!A12,-MonthlyInvestment,0) -> 3654.3609
A13: 5 | B13: =FV( _xlfn.XLOOKUP(Sheet1!$D$59,Scenario_Analysis!$A$3:$A$5,Scenario_Analysis!$B$3:$B$5),Scenario_Analysis!A13,-MonthlyInvestment,0) -> 4590.9045
A14: 6 | B14: =FV( _xlfn.XLOOKUP(Sheet1!$D$59,Scenario_Analysis!$A$3:$A$5,Scenario_Analysis!$B$3:$B$5),Scenario_Analysis!A14,-MonthlyInvestment,0) -> 5536.8136
A15: 7 | B15: =FV( _xlfn.XLOOKUP(Sheet1!$D$59,Scenario_Analysis!$A$3:$A$5,Scenario_Analysis!$B$3:$B$5),Scenario_Analysis!A15,-MonthlyInvestment,0) -> 6492.1817
A16: 8 | B16: =FV( _xlfn.XLOOKUP(Sheet1!$D$59,Scenario_Analysis!$A$3:$A$5,Scenario_Analysis!$B$3:$B$5),Scenario_Analysis!A16,-MonthlyInvestment,0) -> 7457.1035
A17: 9 | B17: =FV( _xlfn.XLOOKUP(Sheet1!$D$59,Scenario_Analysis!$A$3:$A$5,Scenario_Analysis!$B$3:$B$5),Scenario_Analysis!A17,-MonthlyInvestment,0) -> 8431.6745
A18: 10 | B18: =FV( _xlfn.XLOOKUP(Sheet1!$D$59,Scenario_Analysis!$A$3:$A$5,Scenario_Analysis!$B$3:$B$5),Scenario_Analysis!A18,-MonthlyInvestment,0) -> 9415.9913
A19: 11 | B19: =FV( _xlfn.XLOOKUP(Sheet1!$D$59,Scenario_Analysis!$A$3:$A$5,Scenario_Analysis!$B$3:$B$5),Scenario_Analysis!A19,-MonthlyInvestment,0) -> 10410.151
A20: 12 | B20: =FV( _xlfn.XLOOKUP(Sheet1!$D$59,Scenario_Analysis!$A$3:$A$5,Scenario_Analysis!$B$3:$B$5),Scenario_Analysis!A20,-MonthlyInvestment,0) -> 11414.253
... A68: 60 | B68: =FV( _xlfn.XLOOKUP(Sheet1!$D$59,Scenario_Analysis!$A$3:$A$5,Scenario_Analysis!$B$3:$B$5),Scenario_Analysis!A68,-MonthlyInvestment,0) -> 73502.703

Sheet Profile
A2: KEY | B2: PROFILE | C2: TYPE OF REIT (FII) | D2: %
A3: =B3&"-"&C3 -> Conservative-Paper | B3: Conservative | C3: Paper | D3: 0.3
A4: =B4&"-"&C4 -> Conservative-Brick | B4: Conservative | C4: Brick | D4: 0.5
A5: =B5&"-"&C5 -> Conservative-Hybrid | B5: Conservative | C5: Hybrid | D5: 0.1
A6: =B6&"-"&C6 -> Conservative-Funds of Funds | B6: Conservative | C6: Funds of Funds | D6: 0.1
A7: =B7&"-"&C7 -> Conservative-Development | B7: Conservative | C7: Development | D7: 0
A8: =B8&"-"&C8 -> Conservative-Hospitality | B8: Conservative | C8: Hospitality | D8: 0
A9: =B9&"-"&C9 -> Moderate-Paper | B9: Moderate | C9: Paper | D9: 0.32
A10: =B10&"-"&C10 -> Moderate-Brick | B10: Moderate | C10: Brick | D10: 0.35
A11: =B11&"-"&C11 -> Moderate-Hybrid | B11: Moderate | C11: Hybrid | D11: 0.08
A12: =B12&"-"&C12 -> Moderate-Funds of Funds | B12: Moderate | C12: Funds of Funds | D12: 0.05
A13: =B13&"-"&C13 -> Moderate-Development | B13: Moderate | C13: Development | D13: 0.1
A14: =B14&"-"&C14 -> Moderate-Hospitality | B14: Moderate | C14: Hospitality | D14: 0.1
... A20: =B20&"-"&C20 -> Aggressive-Hospitality | B20: Aggressive | C20: Hospitality | D20: 0.1
